genie/libs/conf/__init__.py
genie/libs/conf/access_list/__init__.py
genie/libs/conf/access_list/access_list.py
genie/libs/conf/acl/__init__.py
genie/libs/conf/acl/acl.py
genie/libs/conf/acl/iosxe/__init__.py
genie/libs/conf/acl/iosxe/acl.py
genie/libs/conf/acl/iosxe/tests/test_acl.py
genie/libs/conf/acl/tests/iosxe/test_acl.py
genie/libs/conf/address_family/__init__.py
genie/libs/conf/arp/__init__.py
genie/libs/conf/arp/arp.py
genie/libs/conf/arp/iosxe/__init__.py
genie/libs/conf/arp/iosxe/arp.py
genie/libs/conf/arp/iosxe/tests/__init__.py
genie/libs/conf/arp/iosxe/tests/test_arp.py
genie/libs/conf/base/__init__.py
genie/libs/conf/base/abc.py
genie/libs/conf/base/feature.py
genie/libs/conf/base/ipaddress.py
genie/libs/conf/base/mac.py
genie/libs/conf/base/neighbor.py
genie/libs/conf/base/password_type.py
genie/libs/conf/base/redistribution_attr.py
genie/libs/conf/base/route_distinguisher.py
genie/libs/conf/base/route_target.py
genie/libs/conf/base/routing.py
genie/libs/conf/base/tests/__init__.py
genie/libs/conf/base/tests/test_route_target.py
genie/libs/conf/bgp/__init__.py
genie/libs/conf/bgp/bgp.py
genie/libs/conf/bgp/bgp_prefix.py
genie/libs/conf/bgp/iosxe/__init__.py
genie/libs/conf/bgp/iosxe/bgp.py
genie/libs/conf/bgp/iosxe/tests/__init__.py
genie/libs/conf/bgp/iosxe/tests/test_bgp.py
genie/libs/conf/bgp/iosxr/__init__.py
genie/libs/conf/bgp/iosxr/bgp.py
genie/libs/conf/bgp/iosxr/tests/__init__.py
genie/libs/conf/bgp/iosxr/tests/test_bgp.py
genie/libs/conf/bgp/nxos/__init__.py
genie/libs/conf/bgp/nxos/bgp.py
genie/libs/conf/bgp/nxos/rest/__init__.py
genie/libs/conf/bgp/nxos/rest/bgp.py
genie/libs/conf/bgp/nxos/tests/__init__.py
genie/libs/conf/bgp/nxos/tests/test_bgp.py
genie/libs/conf/bgp/tests/__init__.py
genie/libs/conf/bgp/tests/test_bgp_prefix.py
genie/libs/conf/bgp/tests/iosxe/__init__.py
genie/libs/conf/bgp/tests/iosxe/test_bgp.py
genie/libs/conf/bgp/tests/iosxr/__init__.py
genie/libs/conf/bgp/tests/iosxr/test_bgp.py
genie.libs.conf-25.9.dist-info/METADATA
genie.libs.conf-25.9.dist-info/WHEEL
genie.libs.conf-25.9.dist-info/top_level.txt
genie.libs.conf-25.9.dist-info/RECORD
